worm_library/__init__.py
worm_library/downloader.py
worm_library-1.0.0.dist-info/licenses/LICENSE
worm_library-1.0.0.dist-info/METADATA
worm_library-1.0.0.dist-info/WHEEL
worm_library-1.0.0.dist-info/top_level.txt
worm_library-1.0.0.dist-info/RECORD
