Metadata-Version: 2.4
Name: worm-library
Version: 1.0.0
Summary: Download WORM Portal tutorial notebooks and demo files
Author: Grayson Boyer
Author-email: Grayson Boyer <gmboyer@asu.edu>
License-Expression: MIT
Project-URL: Homepage, https://github.com/worm-portal/WORM-Library
Project-URL: Repository, https://github.com/worm-portal/WORM-Library
Project-URL: Documentation, https://github.com/worm-portal/WORM-Library
Project-URL: Issues, https://github.com/worm-portal/WORM-Library/issues
Keywords: geochemistry,thermodynamics,aqueous,speciation,tutorials
Classifier: Development Status :: 4 - Beta
Classifier: Intended Audience :: Science/Research
Classifier: Operating System :: OS Independent
Classifier: Programming Language :: Python :: 3
Classifier: Programming Language :: Python :: 3.10
Classifier: Programming Language :: Python :: 3.11
Classifier: Programming Language :: Python :: 3.12
Classifier: Topic :: Scientific/Engineering :: Chemistry
Requires-Python: >=3.10
License-File: LICENSE
Requires-Dist: requests
Requires-Dist: beautifulsoup4
Requires-Dist: lxml
Dynamic: author
Dynamic: license-file
Dynamic: requires-python
